dashboard_demo/wsgi.py
dashboard_demo/__init__.py
dashboard_demo/settings.py
dashboard_demo/urls.py
responsive_dashboard/dashboard.py
responsive_dashboard/tests.py
responsive_dashboard/__init__.py
responsive_dashboard/views.py
responsive_dashboard/models.py
responsive_dashboard/test_urls.py
responsive_dashboard/urls.py
responsive_dashboard/templates/responsive_dashboard/dashlet_add_new.html
responsive_dashboard/templates/responsive_dashboard/dashlet.html
responsive_dashboard/templates/responsive_dashboard/list_dashlet.html
responsive_dashboard/templates/responsive_dashboard/links_list_dashlet.html
responsive_dashboard/templates/responsive_dashboard/dashboard.html
responsive_dashboard/templates/responsive_dashboard/admin_list_dashlet.html
responsive_dashboard/static/responsive_dashboard/responsive_dashboard.js
responsive_dashboard/static/responsive_dashboard/jquery.shapeshift.min.js
responsive_dashboard/static/responsive_dashboard/jquery.ui.touch-punch.min.js
responsive_dashboard/static/responsive_dashboard/jquery-2.1.0.min.js
responsive_dashboard/static/responsive_dashboard/dash.css
responsive_dashboard/static/responsive_dashboard/img/x.svg
responsive_dashboard/static/responsive_dashboard/img/gear.svg
responsive_dashboard/migrations/0001_initial.py
responsive_dashboard/migrations/__init__.py
django_responsive_dashboard-1.3.2.dist-info/metadata.json
django_responsive_dashboard-1.3.2.dist-info/top_level.txt
django_responsive_dashboard-1.3.2.dist-info/DESCRIPTION.rst
django_responsive_dashboard-1.3.2.dist-info/WHEEL
django_responsive_dashboard-1.3.2.dist-info/METADATA
django_responsive_dashboard-1.3.2.dist-info/RECORD
