Metadata-Version: 2.0
Name: django-responsive-dashboard
Version: 1.3.2
Summary: A generic and easy dashboard for Django applications.
Home-page: https://github.com/burke-software/django-responsive-dashboard
Author: David Burke
Author-email: david@burkesoftware.com
License: BSD
Keywords: django dashboard responsive
Platform: UNKNOWN
Classifier: Development Status :: 5 - Production/Stable
Classifier: Environment :: Web Environment
Classifier: Framework :: Django
Classifier: Programming Language :: Python
Classifier: Intended Audience :: Developers
Classifier: Intended Audience :: System Administrators
Classifier: License :: OSI Approved :: BSD License
Requires-Dist: django
Requires-Dist: django-positions
